scylla_go_round/__init__.py
scylla_go_round/common.py
scylla_go_round/go.py
scylla_go_round/main.py
scylla_go_round/scylla.py
scylla_go_round-0.2.0.dist-info/LICENSE
scylla_go_round-0.2.0.dist-info/METADATA
scylla_go_round-0.2.0.dist-info/WHEEL
scylla_go_round-0.2.0.dist-info/entry_points.txt
scylla_go_round-0.2.0.dist-info/RECORD
