Metadata-Version: 2.1
Name: scylla-go-round
Version: 0.2.0
Summary: A CLI tool to generate Go types from ScyllaDB or Cassandra schemas
Home-page: https://github.com/johnlarkin1/scylla-go-round
License: MIT
Keywords: scylla,cassandra,go,cli,schema
Author: John Larkin
Author-email: john@johnjlarkin.com
Requires-Python: >=3.11
Classifier: License :: OSI Approved :: MIT License
Classifier: Programming Language :: Python :: 3
Classifier: Programming Language :: Python :: 3.11
Classifier: Programming Language :: Python :: 3.12
Requires-Dist: cassandra-driver (>=3.29.1,<4.0.0)
Requires-Dist: python-dotenv (>=1.0.1,<2.0.0)
